_pysha3.cpython-39-x86_64-linux-gnu.so
sha3.py
safe_pysha3-1.0.3.dist-info/METADATA
safe_pysha3-1.0.3.dist-info/top_level.txt
safe_pysha3-1.0.3.dist-info/RECORD
safe_pysha3-1.0.3.dist-info/WHEEL
safe_pysha3-1.0.3.dist-info/LICENSE
