Metadata-Version: 2.1
Name: safe-pysha3
Version: 1.0.3
Summary: SHA-3 (Keccak) for Python 3.9 - 3.11
Home-page: https://github.com/5afe/pysha3
Author: Christian Heimes
Author-email: christian@python.org
Maintainer: =?utf-8?b?VXjDrW8gRnVlbnRlZnLDrWE=?=
Maintainer-email: uxio@safe.global
License: PSFL (Keccak: CC0 1.0 Universal)
Keywords: sha3 sha-3 keccak hash
Platform: POSIX
Platform: Windows
Classifier: Development Status :: 4 - Beta
Classifier: Intended Audience :: Developers
Classifier: License :: OSI Approved :: Python Software Foundation License
Classifier: License :: CC0 1.0 Universal (CC0 1.0) Public Domain Dedication
Classifier: Natural Language :: English
Classifier: Operating System :: MacOS :: MacOS X
Classifier: Operating System :: POSIX
Classifier: Operating System :: POSIX :: BSD
Classifier: Operating System :: POSIX :: Linux
Classifier: Operating System :: Microsoft :: Windows
Classifier: Programming Language :: C
Classifier: Programming Language :: Python
Classifier: Programming Language :: Python :: 3.9
Classifier: Programming Language :: Python :: 3.10
Classifier: Programming Language :: Python :: 3.11
Classifier: Topic :: Security :: Cryptography
License-File: LICENSE
